tg_apicore/__init__.py
tg_apicore/apps.py
tg_apicore/docs.py
tg_apicore/pagination.py
tg_apicore/parsers.py
tg_apicore/renderers.py
tg_apicore/routers.py
tg_apicore/schemas.py
tg_apicore/serializers.py
tg_apicore/settings.py
tg_apicore/test.py
tg_apicore/transformers.py
tg_apicore/views.py
tg_apicore/viewsets.py
tg_apicore/static/css/tg_apicore.css
tg_apicore/static/sass/_tg_apicore.scss
tg_apicore/templates/tg_apicore/scopes.html
tg_apicore/templates/tg_apicore/docs/base.html
tg_apicore/templates/tg_apicore/docs/index.html
tg_apicore/templates/tg_apicore/docs/method-python.html
tg_apicore/templates/tg_apicore/docs/method.html
tg_apicore/templates/tg_apicore/docs/section.html
tg_apicore/templates/tg_apicore/docs/sidebar.html
tg_apicore/templatetags/__init__.py
tg_apicore/templatetags/tg_apicore.py
tg_apicore-0.3.0.dist-info/METADATA
tg_apicore-0.3.0.dist-info/RECORD
tg_apicore-0.3.0.dist-info/WHEEL
tg_apicore-0.3.0.dist-info/top_level.txt
