Metadata-Version: 2.1
Name: tg-apicore
Version: 0.3.0
Summary: Opinionated API framework on top of Django REST framework
Home-page: https://github.com/thorgate/tg-apicore
Author: Thorgate
Author-email: code@thorgate.eu
License: ISC license
Keywords: tg-apicore django djangorestframework
Platform: UNKNOWN
Classifier: Development Status :: 2 - Pre-Alpha
Classifier: Intended Audience :: Developers
Classifier: License :: OSI Approved :: ISC License (ISCL)
Classifier: Natural Language :: English
Classifier: Programming Language :: Python :: 3
Classifier: Programming Language :: Python :: 3.5
Classifier: Programming Language :: Python :: 3.6
Requires-Dist: Django (<2.1,>=1.11)
Requires-Dist: djangorestframework (<4,>=3.6)
Requires-Dist: djangorestframework-jsonapi (<3,>=2.4)
Requires-Dist: attrs (>=17.2.0)
Requires-Dist: coreapi (>=2.3)
Requires-Dist: Markdown (>=2.6)
Requires-Dist: Pygments (>=2.2)
